[
  {
    "journal": {
      "ja": "医用イメージングジャーナル",
      "en": "Journal of Medical Imaging"
    },
    "title": {
      "ja": "腫瘍検出のための新規アルゴリズム",
      "en": "Novel Algorithm for Tumor Detection"
    },
    "desc": {
      "ja": "MRI画像における腫瘍検出精度を向上させる画期的な研究。",
      "en": "A groundbreaking study on enhancing tumor detection accuracy in MRI scans."
    },
    "img": "/publications/ct-scan.jpg",
    "arxivUrl": "https://arxiv.org/abs/1234.5678"
  },
  {
    "journal": {
      "ja": "生体工学ジャーナル",
      "en": "Biomedical Engineering Journal"
    },
    "title": {
      "ja": "超音波画像の解像度向上",
      "en": "Improving Image Resolution in Ultrasound"
    },
    "desc": {
      "ja": "超音波画像の解像度を高める新技術の研究。",
      "en": "Research on new techniques to enhance the resolution of ultrasound images."
    },
    "img": "/publications/ultrasound.jpg",
    "arxivUrl": ""
  }
]
